ai_cli.py
xibe_chat_cli-1.5.8.dist-info/licenses/LICENSE
xibe_chat_cli-1.5.8.dist-info/METADATA
xibe_chat_cli-1.5.8.dist-info/WHEEL
xibe_chat_cli-1.5.8.dist-info/entry_points.txt
xibe_chat_cli-1.5.8.dist-info/top_level.txt
xibe_chat_cli-1.5.8.dist-info/RECORD
