Metadata-Version: 2.4
Name: xibe-chat-cli
Version: 1.5.8
Summary: XIBE-CHAT CLI - AI-powered terminal assistant for text and image generation
Home-page: https://github.com/iotserver24/xibe-chat-cli
Author: iotserver24
Author-email: iotserver24 <iotserver24@gmail.com>
License: Proprietary
Project-URL: Homepage, https://github.com/iotserver24/xibe-chat-cli
Project-URL: Repository, https://github.com/iotserver24/xibe-chat-cli
Project-URL: Documentation, https://github.com/iotserver24/xibe-chat-cli#readme
Project-URL: Bug Tracker, https://github.com/iotserver24/xibe-chat-cli/issues
Keywords: ai,chat,cli,image-generation,text-generation,terminal,assistant
Classifier: Development Status :: 4 - Beta
Classifier: Intended Audience :: End Users/Desktop
Classifier: License :: Other/Proprietary License
Classifier: Operating System :: OS Independent
Classifier: Programming Language :: Python :: 3
Classifier: Programming Language :: Python :: 3.8
Classifier: Programming Language :: Python :: 3.9
Classifier: Programming Language :: Python :: 3.10
Classifier: Programming Language :: Python :: 3.11
Classifier: Programming Language :: Python :: 3.12
Classifier: Topic :: Communications :: Chat
Classifier: Topic :: Scientific/Engineering :: Artificial Intelligence
Classifier: Topic :: Multimedia :: Graphics
Classifier: Topic :: System :: Shells
Requires-Python: >=3.8
License-File: LICENSE
Requires-Dist: pyfiglet>=0.8
Requires-Dist: python-dotenv>=1.0.0
Requires-Dist: requests>=2.28.0
Requires-Dist: rich>=13.0.0
Requires-Dist: prompt-toolkit>=3.0.0
Provides-Extra: dev
Requires-Dist: build>=0.10.0; extra == "dev"
Requires-Dist: twine>=4.0.0; extra == "dev"
Requires-Dist: pytest>=7.0.0; extra == "dev"
Requires-Dist: black>=22.0.0; extra == "dev"
Requires-Dist: flake8>=5.0.0; extra == "dev"
Dynamic: author
Dynamic: home-page
Dynamic: license-file
Dynamic: requires-python
